project/__init__.py
project/config.py
project/main.py
domoskanonos_python_starter-0.4.3.dist-info/METADATA
domoskanonos_python_starter-0.4.3.dist-info/WHEEL
domoskanonos_python_starter-0.4.3.dist-info/licenses/LICENSE
domoskanonos_python_starter-0.4.3.dist-info/RECORD
