Metadata-Version: 2.4
Name: domoskanonos-python-starter
Version: 0.4.3
Summary: python project starter template
Author-email: Dominik Bruhn <dominikbruhn@googlemail.com>
License: MIT
License-File: LICENSE
Requires-Python: >=3.12
Requires-Dist: pydantic-settings>=2.12.0
Requires-Dist: pytest-asyncio>=0.23.0
Requires-Dist: pytest>=8.4.2
Requires-Dist: python-dotenv>=1.1.1
